gunslinger/__init__.py
gunslinger-0.0.1.dist-info/METADATA
gunslinger-0.0.1.dist-info/WHEEL
gunslinger-0.0.1.dist-info/top_level.txt
gunslinger-0.0.1.dist-info/RECORD
